pyTigerGraph/__init__.py
pyTigerGraph/pyTigerGraph.py
pyTigerGraph/pyTigerGraphAuth.py
pyTigerGraph/pyTigerGraphBase.py
pyTigerGraph/pyTigerGraphEdge.py
pyTigerGraph/pyTigerGraphException.py
pyTigerGraph/pyTigerGraphGSQL.py
pyTigerGraph/pyTigerGraphLoading.py
pyTigerGraph/pyTigerGraphPath.py
pyTigerGraph/pyTigerGraphQuery.py
pyTigerGraph/pyTigerGraphSchema.py
pyTigerGraph/pyTigerGraphUDT.py
pyTigerGraph/pyTigerGraphUtils.py
pyTigerGraph/pyTigerGraphVertex.py
pyTigerGraph/gds/__init__.py
pyTigerGraph/gds/dataloaders.py
pyTigerGraph/gds/featurizer.py
pyTigerGraph/gds/gds.py
pyTigerGraph/gds/metrics.py
pyTigerGraph/gds/splitters.py
pyTigerGraph/gds/utilities.py
pyTigerGraph/gds/__pycache__/__init__.cpython-39.pyc
pyTigerGraph/gds/__pycache__/dataloaders.cpython-39.pyc
pyTigerGraph/gds/__pycache__/featurizer.cpython-39.pyc
pyTigerGraph/gds/__pycache__/gds.cpython-39.pyc
pyTigerGraph/gds/__pycache__/metrics.cpython-39.pyc
pyTigerGraph/gds/__pycache__/splitters.cpython-39.pyc
pyTigerGraph/gds/__pycache__/utilities.cpython-39.pyc
pyTigerGraph/gds/gsql/dataloaders/edge_hloader.gsql
pyTigerGraph/gds/gsql/dataloaders/edge_kloader.gsql
pyTigerGraph/gds/gsql/dataloaders/graph_hloader.gsql
pyTigerGraph/gds/gsql/dataloaders/graph_kloader.gsql
pyTigerGraph/gds/gsql/dataloaders/neighbor_hloader.gsql
pyTigerGraph/gds/gsql/dataloaders/neighbor_kloader.gsql
pyTigerGraph/gds/gsql/dataloaders/vertex_hloader.gsql
pyTigerGraph/gds/gsql/dataloaders/vertex_kloader.gsql
pyTigerGraph/gds/gsql/splitters/random_edge_split.gsql
pyTigerGraph/gds/gsql/splitters/random_vertex_split.gsql
tests/__init__.py
tests/pyTigerGraphUnitTest.py
tests/test_gds_BaseLoader.py
tests/test_gds_EdgeLoader.py
tests/test_gds_GraphLoader.py
tests/test_gds_NeighborLoader.py
tests/test_gds_VertexLoader.py
tests/test_gds_dataloaders.py
tests/test_gds_featurizer.py
tests/test_gds_metrics.py
tests/test_gds_splitters.py
tests/test_gds_utilities.py
tests/test_pyTigerGraphAuth.py
tests/test_pyTigerGraphBase.py
pyTigerGraphBeta-0.0.9.9.2.dist-info/METADATA
pyTigerGraphBeta-0.0.9.9.2.dist-info/WHEEL
pyTigerGraphBeta-0.0.9.9.2.dist-info/top_level.txt
pyTigerGraphBeta-0.0.9.9.2.dist-info/RECORD
