Metadata-Version: 2.1
Name: pyTigerGraphBeta
Version: 0.0.9.9.2
Summary: Library to connect to TigerGraph databases
Home-page: https://www.tigergraph.com/
Download-URL: 
Author: TigerGraph Inc.
Author-email: support@tigergraph.com
License: MIT
Project-URL: Bug Reports, https://github.com/pyTigerGraph/pyTigerGraph/issues
Project-URL: Source, https://github.com/pyTigerGraph/pyTigerGraph
Keywords: TigerGraph,Graph Database,Data Science,Machine Learning
Classifier: Development Status :: 4 - Beta
Classifier: Intended Audience :: Developers
Classifier: Topic :: Software Development :: Build Tools
Classifier: License :: OSI Approved :: MIT License
Classifier: Programming Language :: Python :: 3
Classifier: Programming Language :: Python :: 3.4
Classifier: Programming Language :: Python :: 3.5
Classifier: Programming Language :: Python :: 3.6
Classifier: Programming Language :: Python :: 3.7
Classifier: Programming Language :: Python :: 3.8
Classifier: Programming Language :: Python :: 3.9
Classifier: Programming Language :: Python :: 3.10
Requires-Dist: pyTigerDriver
Requires-Dist: validators
Requires-Dist: requests
Provides-Extra: gds
Requires-Dist: pandas ; extra == 'gds'
Requires-Dist: kafka-python ; extra == 'gds'
Requires-Dist: numpy ; extra == 'gds'
Requires-Dist: torch ; extra == 'gds'
Requires-Dist: torch-sparse ; extra == 'gds'
Requires-Dist: torch-scatter ; extra == 'gds'
Requires-Dist: torch-geometric ; extra == 'gds'
Requires-Dist: dgl ; extra == 'gds'
Provides-Extra: gds-dgl
Requires-Dist: pandas ; extra == 'gds-dgl'
Requires-Dist: kafka-python ; extra == 'gds-dgl'
Requires-Dist: numpy ; extra == 'gds-dgl'
Requires-Dist: torch ; extra == 'gds-dgl'
Requires-Dist: dgl ; extra == 'gds-dgl'
Provides-Extra: gds-lite
Requires-Dist: pandas ; extra == 'gds-lite'
Requires-Dist: kafka-python ; extra == 'gds-lite'
Requires-Dist: numpy ; extra == 'gds-lite'
Provides-Extra: gds-pyg
Requires-Dist: pandas ; extra == 'gds-pyg'
Requires-Dist: kafka-python ; extra == 'gds-pyg'
Requires-Dist: numpy ; extra == 'gds-pyg'
Requires-Dist: torch ; extra == 'gds-pyg'
Requires-Dist: torch-sparse ; extra == 'gds-pyg'
Requires-Dist: torch-scatter ; extra == 'gds-pyg'
Requires-Dist: torch-geometric ; extra == 'gds-pyg'
